ambt/__init__.py
ambt/exports.py
ambt/resources/template/pwntools
ambt/tools/__init__.py
ambt/tools/cli.py
ambt/tools/patcher.py
ambt/tools/template.py
ambt/utils/__init__.py
ambt/utils/packing.py
ambt/utils/runtime.py
ambt/utils/tube.py
ambt/utils/typing.py
ambt-0.1.0.dist-info/LICENSE
ambt-0.1.0.dist-info/METADATA
ambt-0.1.0.dist-info/WHEEL
ambt-0.1.0.dist-info/entry_points.txt
ambt-0.1.0.dist-info/RECORD
