Metadata-Version: 2.3
Name: ambt
Version: 0.1.0
Summary: make pwning less painful
Author: k1R4
Author-email: srijiith@outlook.com
Requires-Python: >=3.6,<4.0
Classifier: Programming Language :: Python :: 3
Classifier: Programming Language :: Python :: 3.6
Classifier: Programming Language :: Python :: 3.7
Classifier: Programming Language :: Python :: 3.8
Classifier: Programming Language :: Python :: 3.9
Classifier: Programming Language :: Python :: 3.10
Classifier: Programming Language :: Python :: 3.11
Classifier: Programming Language :: Python :: 3.12
Classifier: Programming Language :: Python :: 3.13
Requires-Dist: pwntools (>=4.14.0,<5.0.0)
Requires-Dist: unix-ar (>=0.2.1,<0.3.0)
Project-URL: Documentation, https://github.com/k1R4/ambt
Project-URL: Homepage, https://github.com/k1R4/ambt
Project-URL: Repository, https://github.com/k1R4/ambt
